_runtime.abi3.so
koi_cuda113.libs/lib-718eb85d.so
koi_cuda113-0.0.5.dist-info/METADATA
koi_cuda113-0.0.5.dist-info/RECORD
koi_cuda113-0.0.5.dist-info/WHEEL
koi_cuda113-0.0.5.dist-info/top_level.txt
koi/build.py
koi/__init__.py
koi/decode.py
koi/utils.py
koi/lstm.py
koi/test/test_lstm.py
koi/test/__init__.py
